sakke/__init__.py
sakke/sakke.py
sakke/templates/stats.html.j2
sakke/templates/stats.tex.j2
sakke-2.0.11.dist-info/LICENSE
sakke-2.0.11.dist-info/METADATA
sakke-2.0.11.dist-info/WHEEL
sakke-2.0.11.dist-info/entry_points.txt
sakke-2.0.11.dist-info/top_level.txt
sakke-2.0.11.dist-info/RECORD
